linkzone/__init__.py
linkzone/version.py
linkzone/client/__init__.py
linkzone/client/authentication.py
linkzone/client/information.py
linkzone/client/sms.py
linkzone/client/ussd.py
linkzone/common/__init__.py
linkzone/common/config.json
linkzone/common/config.py
linkzone/common/data_models.py
linkzone/common/exceptions.py
linkzone/core/__init__.py
linkzone/core/base_api_client.py
linkzone/core/interfaces/__init__.py
linkzone/core/interfaces/request_handler.py
linkzone/core/interfaces/response_handler.py
linkzone/core/services/__init__.py
linkzone/core/services/request_service.py
linkzone/core/services/response_service.py
linkzone-0.1.2.dist-info/LICENSE
linkzone-0.1.2.dist-info/METADATA
linkzone-0.1.2.dist-info/WHEEL
linkzone-0.1.2.dist-info/top_level.txt
linkzone-0.1.2.dist-info/RECORD
