Metadata-Version: 2.1
Name: linkzone
Version: 0.1.2
Summary: SDK for Alcatel Linkzone modems: MW41NF, MW41CL
Author-email: Jimmy Angel Pérez Díaz <jianpedi@gmail.com>
License: MIT License
Project-URL: Source, https://github.com/JimScope/linkzone
Keywords: alcatel,linkzone,SDK,API,SMS
Classifier: License :: OSI Approved :: MIT License
Classifier: Programming Language :: Python :: 3.12
Classifier: Intended Audience :: Developers
Classifier: Operating System :: OS Independent
Classifier: Topic :: Communications :: Internet Phone
Classifier: Topic :: Internet
Classifier: Topic :: Software Development :: Libraries
Requires-Python: >=3.10
License-File: LICENSE
Requires-Dist: requests
Provides-Extra: dev
Requires-Dist: pytest; extra == "dev"
Requires-Dist: black; extra == "dev"
Provides-Extra: docs
Requires-Dist: sphinx; extra == "docs"
Requires-Dist: sphinx-rtd-theme; extra == "docs"
